meeshkan_hosted_db/__init__.py
meeshkan_hosted_db-0.2.dist-info/LICENSE
meeshkan_hosted_db-0.2.dist-info/METADATA
meeshkan_hosted_db-0.2.dist-info/WHEEL
meeshkan_hosted_db-0.2.dist-info/top_level.txt
meeshkan_hosted_db-0.2.dist-info/RECORD
