Metadata-Version: 2.1
Name: meeshkan-hosted-db
Version: 0.2
Summary: Utility package to access a Cloud SQL database on meeshkan.io
Home-page: https://github.com/meeshkan/meeshkan-hosted-db
Author: Meeshkan Dev Team
Author-email: dev@meeshkan.com
License: MIT
Platform: UNKNOWN
Requires-Dist: meeshkan-hosted-secrets (>=0.4)
Requires-Dist: psycopg2-binary (==2.8.5)
